{
  "last_updated": "2026-03-06T10:36:47.567Z",
  "last_updated_IST": "6/3/2026, 4:06:47 pm",
  "total_articles": 402,
  "categories": [
    "telangana",
    "business",
    "tech",
    "india",
    "sports",
    "andhra"
  ],
  "sources": [
    "Sakshi",
    "The Hindu Telangana",
    "LiveMint",
    "Dev.to",
    "The Hindu",
    "NDTV",
    "India Today",
    "YourStory",
    "Times of India",
    "ZDNet",
    "Wired",
    "NDTV India",
    "Hindustan Times",
    "ESPNCricinfo",
    "Economic Times",
    "Inc42",
    "The Hindu AP",
    "TechCrunch",
    "The Verge",
    "Moneycontrol"
  ],
  "feeds_count": 25,
  "data_files": [
    "news.json",
    "telangana.json",
    "business.json",
    "tech.json",
    "india.json",
    "sports.json",
    "andhra.json"
  ]
}