{
  "last_updated": "2026-03-07T06:36:13.639Z",
  "last_updated_IST": "7/3/2026, 12:06:13 pm",
  "total_articles": 383,
  "categories": [
    "india",
    "business",
    "tech",
    "andhra",
    "telangana",
    "sports"
  ],
  "sources": [
    "The Hindu",
    "LiveMint",
    "Dev.to",
    "NDTV",
    "Times of India",
    "Hindustan Times",
    "NDTV India",
    "Economic Times",
    "YourStory",
    "India Today",
    "Inc42",
    "ZDNet",
    "The Verge",
    "TechCrunch",
    "The Hindu AP",
    "Wired",
    "The Hindu Telangana",
    "ESPNCricinfo"
  ],
  "feeds_count": 25,
  "data_files": [
    "news.json",
    "india.json",
    "business.json",
    "tech.json",
    "andhra.json",
    "telangana.json",
    "sports.json"
  ]
}