{
  "last_updated": "2026-03-03T18:44:06.981Z",
  "last_updated_IST": "4/3/2026, 12:14:06 am",
  "total_articles": 373,
  "categories": [
    "tech",
    "business",
    "sports",
    "india",
    "telangana",
    "andhra"
  ],
  "sources": [
    "The Verge",
    "TechCrunch",
    "LiveMint",
    "ESPNCricinfo",
    "Dev.to",
    "The Hindu",
    "India Today",
    "NDTV",
    "Hindustan Times",
    "Times of India",
    "The Hindu Telangana",
    "ZDNet",
    "The Hindu AP",
    "NDTV India",
    "YourStory",
    "Wired",
    "Inc42",
    "Economic Times"
  ],
  "feeds_count": 25,
  "data_files": [
    "news.json",
    "tech.json",
    "business.json",
    "sports.json",
    "india.json",
    "telangana.json",
    "andhra.json"
  ]
}