{
  "updated_at": "2026-03-25T09:53:46.413Z",
  "updated_at_IST": "25/3/2026, 3:23:46 pm",
  "category": "telangana",
  "count": 20,
  "articles": [
    {
      "id": "e0db0e7de8cb63f3b6ebe8e556cc4e2d",
      "title": "Approximately 20,000 kilolitres of petrol available, no fuel shortage in any part of Telangana: Civil Supplies Commissioner",
      "summary": "Minister Raveendra claimed that 1,500 petrol and diesel tankers are on standby, supplying fuel to stations in this emergency",
      "url": "https://www.thehindu.com/news/national/telangana/approximately-20000-kilolitres-of-petrol-available-no-fuel-shortage-in-any-part-of-telangana-civil-supplies-commissioner/article70783046.ece",
      "image": "https://th-i.thgim.com/public/incoming/wsndmb/article70783041.ece/alternates/LANDSCAPE_1200/_NGP5744.JPG",
      "published_at": "2026-03-25T08:08:32.000Z",
      "source": "The Hindu Telangana",
      "category": "telangana",
      "language": "en",
      "title_te": "దాదాపు 20,000 కిలోలీటర్ల పెట్రోల్ అందుబాటులో ఉంది, తెలంగాణలోని ఏ ప్రాంతంలోనూ ఇంధన కొరత లేదు: పౌర సరఫరాల కమిషనర్",
      "summary_te": "1,500 పెట్రోల్, డీజిల్ ట్యాంకర్లు సిద్ధంగా ఉన్నాయని, ఈ అత్యవసర పరిస్థితుల్లో స్టేషన్లకు ఇంధనాన్ని సరఫరా చేస్తున్నామని మంత్రి రవీంద్ర పేర్కొన్నారు.",
      "translated": true
    },
    {
      "id": "ab3b217048696438f82f0df4bdbe838f",
      "title": "Delimitation exercise will make Southern States irrelevant in national politics: Telangana CM",
      "summary": "Revanth Reddy says issues related to the Southern states too will become irrelevant",
      "url": "https://www.thehindu.com/news/national/telangana/delimitation-exercise-will-make-southern-states-irrelevant-in-national-politics-telangana-cm/article70781112.ece",
      "image": "https://th-i.thgim.com/public/incoming/4802rh/article70783236.ece/alternates/LANDSCAPE_1200/_DSC7548.JPG",
      "published_at": "2026-03-25T08:06:29.000Z",
      "source": "The Hindu Telangana",
      "category": "telangana",
      "language": "en",
      "title_te": "డీలిమిటేషన్ కసరత్తు దక్షిణాది రాష్ట్రాలను జాతీయ రాజకీయాల్లో అప్రస్తుతం: తెలంగాణ సీఎం",
      "summary_te": "దక్షిణాది రాష్ట్రాలకు సంబంధించిన అంశాలు కూడా అప్రస్తుతం కానున్నాయని రేవంత్ రెడ్డి అంటున్నారు",
      "translated": true
    },
    {
      "id": "dbf6c750698618f5241063bbe116aac6",
      "title": "No fuel shortage in Telangana: Petroleum Dealers Association",
      "summary": "Rumour-driven panic buying triggers three-fold surge in fuel sales, says the association on March 25, 2026",
      "url": "https://www.thehindu.com/news/national/telangana/no-fuel-shortage-in-telangana-petroleum-dealers-association/article70782805.ece",
      "image": "https://th-i.thgim.com/public/incoming/9g61l0/article70782848.ece/alternates/LANDSCAPE_1200/DSC2081.jpg",
      "published_at": "2026-03-25T07:31:16.000Z",
      "source": "The Hindu Telangana",
      "category": "telangana",
      "language": "en",
      "title_te": "తెలంగాణలో ఇంధన కొరత లేదు: పెట్రోలియం డీలర్ల సంఘం",
      "summary_te": "పుకారుతో నడిచే భయాందోళనల కొనుగోలు ఇంధన విక్రయాలలో మూడు రెట్లు పెరుగుదలను ప్రేరేపిస్తుంది, మార్చి 25, 2026న అసోసియేషన్ తెలిపింది",
      "translated": true
    },
    {
      "id": "94651a9ffbf7773f3162af56746d8526",
      "title": "Rush at Hyderabad fuel outlets for second day; people join serpentine queues from March 25 early morning",
      "summary": "Telangana Civil Supplies Department on Tuesday (March 24, 2026) attributed the ‘no stock’ boards at some of the outlets to sudden panic driven buying",
      "url": "https://www.thehindu.com/news/cities/Hyderabad/serpentine-queues-at-hyderabad-fuel-outlets-for-the-second-day/article70782472.ece",
      "image": "https://th-i.thgim.com/public/incoming/6zi7m4/article70782609.ece/alternates/LANDSCAPE_1200/DSC2206.jpg",
      "published_at": "2026-03-25T07:28:52.000Z",
      "source": "The Hindu Telangana",
      "category": "telangana",
      "language": "en",
      "title_te": "హైదరాబాద్ ఇంధన విక్రయ కేంద్రాల్లో రెండో రోజు రద్దీ; ప్రజలు మార్చి 25 తెల్లవారుజాము నుండి సర్ప క్యూలలో చేరారు",
      "summary_te": "తెలంగాణ పౌరసరఫరాల శాఖ మంగళవారం (మార్చి 24, 2026) కొన్ని అవుట్‌లెట్‌లలో ‘నో స్టాక్’ బోర్డులు ఆకస్మిక భయాందోళనతో నడిచే కొనుగోళ్లకు కారణమని పేర్కొంది.",
      "translated": true
    },
    {
      "id": "fcba2bef677fb11f1b443014e5ffc186",
      "title": "No fuel shortage in Hyderabad, says Collector",
      "summary": "Hyderabad District Collector Hari Chandana Dasari on Wednesday (March 25, 2026) clarified that there is no shortage of fuel in the district, amid concerns triggered by circulating rumours.In a statement, the Collector said that all 181 petrol pumps in Hyderabad district are fully operational and adequately stocked, ensuring uninterrupted availability of fuel. She stressed that there is absolutely no scarcity of petrol or diesel and urged motorists not to believe or spread false information.",
      "url": "https://www.thehindu.com/news/cities/Hyderabad/no-fuel-shortage-in-hyderabad-says-collector/article70782900.ece",
      "image": "https://th-i.thgim.com/public/incoming/ogfvqd/article70782985.ece/alternates/LANDSCAPE_1200/_NGP5744.JPG",
      "published_at": "2026-03-25T07:06:42.000Z",
      "source": "The Hindu Telangana",
      "category": "telangana",
      "language": "en",
      "title_te": "హైదరాబాద్‌లో ఇంధన కొరత లేదని కలెక్టర్‌ తెలిపారు",
      "summary_te": "హైదరాబాద్ జిల్లా కలెక్టర్ హరి చందన దాసరి బుధవారం (మార్చి 25, 2026) పుకార్లు వ్యాపించడంతో ఆందోళన చెందుతున్న నేపథ్యంలో జిల్లాలో ఇంధన కొరత లేదని స్పష్టం చేశారు.హైదరాబాద్ జిల్లాలోని మొత్తం 181 పెట్రోల్ పంపులు పూర్తిస్థాయిలో పని చేస్తున్నాయని, ఇంధనం అంతరాయం లేకుండా తగినంత నిల్వ ఉందని కలెక్టర్ ఒక ప్రకటనలో తెలిపారు. పెట్రోల్ లేదా డీజిల్‌కు ఎలాంటి కొరత లేదని, తప్పుడు సమాచారాన్ని నమ్మవద్దని, ప్రచారం చేయవద్దని వాహనదారులను ఆమె ఉద్ఘాటించారు.",
      "translated": true
    },
    {
      "id": "455ac02032b1d019d70cf6b991a08321",
      "title": "Panic over fuel supply chokes Hyderabad roads on March 25, traffic grinds to a crawl during morning rush hour",
      "summary": "Police enforce queues with joint traffic and law-and-order personnel deployment to ease congestion. Old Mumbai Highway, Gachibowli and Lakdikapul emerge as key pressure points as fuel lines spill onto carriageways",
      "url": "https://www.thehindu.com/news/cities/Hyderabad/panic-over-fuel-supply-chokes-hyderabad-roads-traffic-grinds-to-a-crawl-during-rush-hour/article70782664.ece",
      "image": "https://th-i.thgim.com/public/incoming/jd6f1k/article70782738.ece/alternates/LANDSCAPE_1200/DSC2121.jpg",
      "published_at": "2026-03-25T05:41:58.000Z",
      "source": "The Hindu Telangana",
      "category": "telangana",
      "language": "en",
      "title_te": "ఇంధన సరఫరాపై భయాందోళనలు మార్చి 25 న హైదరాబాద్ రోడ్లను ఉక్కిరిబిక్కిరి చేస్తాయి, ఉదయం రద్దీ సమయంలో ట్రాఫిక్ క్రాల్ అవుతుంది",
      "summary_te": "రద్దీని తగ్గించడానికి పోలీసులు ఉమ్మడి ట్రాఫిక్ మరియు శాంతిభద్రతల సిబ్బందిని మోహరించడంతో క్యూలను అమలు చేస్తారు. పాత ముంబయి హైవే, గచ్చిబౌలి మరియు లక్డికాపూల్ క్యారేజ్‌వేలపైకి ఇంధన లైన్లు స్పిరించడంతో కీలక పీడన కేంద్రాలుగా మారాయి.",
      "translated": true
    },
    {
      "id": "f8deeca0da317255e7d11718d6e6ee3e",
      "title": "Telangana CM’s emergency meeting on petrol, LPG and urea stocks on March 25 afternoon",
      "summary": "Urea stocks too would be discussed at the meeting with officials",
      "url": "https://www.thehindu.com/news/national/telangana/telangana-cms-meeting-on-petrol-lpg-and-urea-stocks-on-march-25-afternoon/article70782656.ece",
      "image": "https://th-i.thgim.com/public/incoming/pmc614/article70782670.ece/alternates/LANDSCAPE_1200/DSC2113.jpg",
      "published_at": "2026-03-25T05:14:08.000Z",
      "source": "The Hindu Telangana",
      "category": "telangana",
      "language": "en",
      "title_te": "మార్చి 25 మధ్యాహ్నం పెట్రోల్, ఎల్‌పీజీ, యూరియా నిల్వలపై తెలంగాణ సీఎం అత్యవసర సమావేశం",
      "summary_te": "యూరియా నిల్వలపైనా అధికారులతో సమావేశంలో చర్చించనున్నారు",
      "translated": true
    },
    {
      "id": "73624792614af8d23b8797fc75a0f251",
      "title": "Panic buying led to ‘no stock’ boards; no shortage of petrol, diesel or LPG in Telangana: Civil Supplies dept",
      "summary": "Panic buying leading to ‘no stock’ boards; Hyderabad Police Commissioner too says there is no fuel shortage",
      "url": "https://www.thehindu.com/news/national/telangana/no-shortage-of-petrol-diesel-or-lpg-telangana-govt/article70778739.ece",
      "image": "https://th-i.thgim.com/public/incoming/qpdt5k/article70779707.ece/alternates/LANDSCAPE_1200/fuel%20shortage%2002.jpg",
      "published_at": "2026-03-24T18:42:12.000Z",
      "source": "The Hindu Telangana",
      "category": "telangana",
      "language": "en",
      "title_te": "భయాందోళనల కొనుగోలు 'నో స్టాక్' బోర్డులకు దారితీసింది; తెలంగాణలో పెట్రోల్, డీజిల్ లేదా LPG కొరత లేదు: పౌర సరఫరాల శాఖ",
      "summary_te": "'నో స్టాక్' బోర్డులకు దారితీసే భయాందోళన కొనుగోలు; హైదరాబాద్ పోలీస్ కమిషనర్ కూడా ఇంధన కొరత లేదని చెప్పారు",
      "translated": true
    },
    {
      "id": "15c40e36c70d1f00ece799a6b6551ab6",
      "title": "Fuel shortage fears grip Hyderabad; demand spills over into March 24 night",
      "summary": "Hyderabad woke up on Tuesday to the sight of a city inching forward on fumes, not because fuel had run out, but because fear had taken over.By late Monday night, the first signs of unease began to surface at a quiet petrol pump along Ramanthapur main road. On most evenings, the station serves a handful of customers at a time. That night, however, the trickle turned into a stream. Within minutes, motorcycles began clustering near the dispensers, autos lined up in a row, and cars spilled out on to the main road.",
      "url": "https://www.thehindu.com/news/cities/Hyderabad/fuel-shortage-fears-grip-hyderabad-panic-buying-chokes-petrol-pumps/article70781007.ece",
      "image": "https://th-i.thgim.com/public/incoming/rfh445/article70780966.ece/alternates/LANDSCAPE_1200/fuel%20shortage%2005.jpg",
      "published_at": "2026-03-24T18:39:25.000Z",
      "source": "The Hindu Telangana",
      "category": "telangana",
      "language": "en",
      "title_te": "హైదరాబాద్‌లో ఇంధన కొరత భయం; డిమాండ్ మార్చి 24 రాత్రికి వ్యాపిస్తుంది",
      "summary_te": "ఇంధనం అయిపోయిందన్న కారణంతో కాదు, భయం ఆవహించినందున పొగలు కక్కుతూ నగరం ముందుకు దూసుకుపోతున్న దృశ్యంతో మంగళవారం హైదరాబాద్ మేల్కొంది. సోమవారం అర్థరాత్రి, రామంతాపూర్ ప్రధాన రహదారి వెంబడి ఉన్న ఒక నిశ్శబ్ద పెట్రోల్ పంపు వద్ద ఆందోళన యొక్క మొదటి సంకేతాలు కనిపించడం ప్రారంభించాయి. చాలా సాయంత్రాలలో, స్టేషన్ ఒకేసారి కొంతమంది వినియోగదారులకు సేవలు అందిస్తుంది. అయితే ఆ రాత్రే ఆ తంతు ప్రవాహంలా మారింది. నిమిషాల వ్యవధిలో, డిస్పెన్సర్‌ల దగ్గర మోటారు సైకిళ్లు గుంపులు గుంపులుగా రావడం ప్రారంభించాయి, ఆటోలు వరుసలో ఉన్నాయి మరియు కార్లు ప్రధాన రహదారిపైకి చిందించబడ్డాయి.",
      "translated": true
    },
    {
      "id": "01e806f92911194981edf468e0db2eaa",
      "title": "Protest against ‘Sunrisers Hyderabad’ team management for neglecting Telangana players",
      "summary": "The Telangana Districts Cricket Association (TDCA) along with student organisations staged a protest at the Rajiv Gandhi International Cricket Stadium demanding greater representation for Telangana players in the Sunrisers Hyderabad squad.The protest was led by TDCA president Allipuram Venkateshwar Reddy, who said Sunrisers Hyderabad owners have the financial capacity to purchase Pakistan leg-spinner Abrar Ahmed for ₹2.34 crore in the 100 League, but it was failing to provide opportunities to talented cricketers from Telangana.They criticised the franchise for spending crores on overseas players while allegedly neglecting local youth. They argued that IPL franchises from Delhi, Mumbai, Chennai and Punjab have provided opportunities to Telugu players, but Sunrisers Hyderabad has not shown similar encouragement towards local cricketers.“You seek Telangana’s market, revenues and resources, but deny playing opportunities to our talented youth. There can be no greater injustice than this,” Mr Reddy said. He demanded that Chief Minister Revanth Reddy, Sports Minister Srihari and Sunrisers Hyderabad owner Kavya Maran respond to the concerns and ensure justice to Telangana cricketers.",
      "url": "https://www.thehindu.com/news/national/telangana/protest-against-sunrisers-hyderabad-team-management-for-neglecting-telangana-players/article70781063.ece",
      "image": "https://www.thehindu.com/theme/images/og-image.png",
      "published_at": "2026-03-24T18:11:47.000Z",
      "source": "The Hindu Telangana",
      "category": "telangana",
      "language": "en",
      "title_te": "తెలంగాణ ఆటగాళ్లను నిర్లక్ష్యం చేస్తున్న ‘సన్‌రైజర్స్ హైదరాబాద్’ టీమ్ మేనేజ్‌మెంట్‌పై నిరసన",
      "summary_te": "సన్‌రైజర్స్ హైదరాబాద్ జట్టులో తెలంగాణ ఆటగాళ్లకు ఎక్కువ ప్రాతినిధ్యం కల్పించాలని డిమాండ్ చేస్తూ తెలంగాణ డిస్ట్రిక్ట్ క్రికెట్ అసోసియేషన్ (టిడిసిఎ), విద్యార్థి సంఘాలు రాజీవ్ గాంధీ ఇంటర్నేషనల్ క్రికెట్ స్టేడియంలో నిరసనకు దిగాయి. సన్‌రైజర్స్ హైదరాబాద్ యాజమాన్యం పాక్ లెగ్ స్పిన్నర్ అబ్రార్ అహ్మద్‌కు లీగ్‌లో 130 కోట్ల రూపాయలకు కొనుగోలు చేసే ఆర్థిక స్తోమత ఉందని టిడిసిఎ అధ్యక్షుడు అల్లిపురం వెంకటేశ్వర్ రెడ్డి నేతృత్వంలో నిరసన తెలిపారు. తెలంగాణకు చెందిన ప్రతిభావంతులైన క్రికెటర్లకు.. ఫ్రాంచైజీ విదేశీ ఆటగాళ్ల కోసం కోట్లకు పడగలెత్తిందని, అయితే స్థానిక యువతను నిర్లక్ష్యం చేస్తోందని వారు విమర్శించారు. ఢిల్లీ, ముంబై, చెన్నై, పంజాబ్‌లకు చెందిన ఐపీఎల్ ఫ్రాంచైజీలు తెలుగు ఆటగాళ్లకు అవకాశాలు కల్పించాయని, అయితే సన్‌రైజర్స్ హైదరాబాద్ స్థానిక క్రికెటర్లకు అలాంటి ప్రోత్సాహాన్ని అందించలేదని వారు వాదించారు. \"మీరు తెలంగాణ మార్కెట్, ఆదాయాలు మరియు వనరులను కోరుకుంటారు, కానీ మా ప్రతిభావంతులైన యువతకు ఆట అవకాశాలను నిరాకరించారు. ఇంతకంటే పెద్ద అన్యాయం మరొకటి ఉండదు,\" అని శ్రీ రెడ్డి అన్నారు. ఈ ఆందోళనలపై ముఖ్యమంత్రి రేవంత్‌రెడ్డి, క్రీడాశాఖ మంత్రి శ్రీహరి, సన్‌రైజర్స్‌ హైదరాబాద్‌ యాజమాన్యం కావ్య మారన్‌ స్పందించి తెలంగాణ క్రికెటర్లకు న్యాయం చేయాలని డిమాండ్‌ చేశారు.",
      "translated": true
    },
    {
      "id": "8a9725e04366af76b482921dbd727136",
      "title": "TGNPDCL bags ‘Governance Now’ award",
      "summary": "HYDERABADThe Northern Power Distribution Company of Telangana Ltd (TGNPDCL) has bagged three Governance Now 12th PSU Award 2026 in the high-impact categories - Operational Excellence, Automation and Digital Technology - cementing its position as a frontrunner in power distribution innovation.According to officials of the Discom, the award was present to the utility at an event held in New Delhi. It was received by Company Secretary of the Discom K. Venkatesham.The trophies were was handed over to Chairman and Managing Director of the Discom K. Varun Reddy at its corporate office in Hanmakonda on Monday. “The award is not just a corporate milestone but it’s a testament to the hard work, dedication and commitment of every employee of TGNPDCL,” the CMD said adding that “it reflects our collective resolve to harness technology and place the consumer at the heart of everything we do.”",
      "url": "https://www.thehindu.com/news/national/telangana/tgnpdcl-bags-governance-now-award/article70776763.ece",
      "image": "https://th-i.thgim.com/public/news/national/telangana/mf049w/article70776755.ece/alternates/LANDSCAPE_1200/WhatsApp%20Image%202026-03-23%20at%201.32.20%20PM.jpeg",
      "published_at": "2026-03-24T18:01:51.000Z",
      "source": "The Hindu Telangana",
      "category": "telangana",
      "language": "en",
      "title_te": "TGNPDCLకి ‘గవర్నెన్స్ నౌ’ అవార్డు లభించింది",
      "summary_te": "హైదరాబాద్ నార్తర్న్ పవర్ డిస్ట్రిబ్యూషన్ కంపెనీ ఆఫ్ తెలంగాణ లిమిటెడ్ (TGNPDCL) మూడు గవర్నెన్స్ నౌ 12వ PSU అవార్డ్ 2026ను అధిక-ప్రభావ కేటగిరీలలో - ఆపరేషనల్ ఎక్సలెన్స్, ఆటోమేషన్ మరియు డిజిటల్ టెక్నాలజీ - పవర్ డిస్‌కామ్‌లో పవర్ డిస్ట్రిబ్యూషన్‌లో అగ్రగామిగా నిలబెట్టింది. న్యూఢిల్లీలో జరిగిన ఒక కార్యక్రమంలో యుటిలిటీ. దీనిని డిస్కమ్ కంపెనీ సెక్రటరీ కె.వెంకటేశం అందుకున్నారు.సోమవారం హన్మకొండలోని కార్పొరేట్ కార్యాలయంలో డిస్కమ్ చైర్మన్ అండ్ మేనేజింగ్ డైరెక్టర్ కె.వరుణ్ రెడ్డికి ట్రోఫీలను అందజేశారు. \"ఈ అవార్డు కేవలం కార్పొరేట్ మైలురాయి మాత్రమే కాదు, ఇది TGNPDCL యొక్క ప్రతి ఉద్యోగి యొక్క కృషి, అంకితభావం మరియు నిబద్ధతకు నిదర్శనం\" అని CMD అన్నారు, \"సాంకేతికతను ఉపయోగించుకోవడం మరియు మేము చేసే ప్రతి పనిలో వినియోగదారుని హృదయంలో ఉంచాలనే మా సమిష్టి సంకల్పాన్ని ఇది ప్రతిబింబిస్తుంది.\"",
      "translated": true
    },
    {
      "id": "fc99cc4718a20fc4c34424f870458600",
      "title": "Illegal pickle unit busted in Hyderabad, one arrested; unhygienic stock worth ₹3 lakh seized",
      "summary": "",
      "url": "https://www.thehindu.com/news/cities/Hyderabad/illegal-pickle-unit-busted-in-hyderabad-one-arrested-unhygienic-stock-worth-3-lakh-seized/article70780337.ece",
      "image": "https://th-i.thgim.com/public/incoming/z6ehgx/article70780328.ece/alternates/LANDSCAPE_1200/Pickle%20adulterated%20.jpeg",
      "published_at": "2026-03-24T18:01:11.000Z",
      "source": "The Hindu Telangana",
      "category": "telangana",
      "language": "en",
      "title_te": "హైదరాబాద్‌లో అక్రమ ఊరగాయ యూనిట్‌ను ఛేదించారు, ఒకరి అరెస్ట్; 3 లక్షల విలువైన అపరిశుభ్రమైన స్టాక్‌ను స్వాధీనం చేసుకున్నారు",
      "summary_te": "",
      "translated": true
    },
    {
      "id": "a30beb39815bf8931ebb0ed5158c6320",
      "title": "TGMREIS students showcase AI projects at literacy event",
      "summary": "More than 2,000 school students of Telangana Minorities Residential Educational Institutions Society (TGMREIS) were equipped with literacy of artificial intelligence and showcased Al-based applications and digital projects they developed.The Al Literacy Showcase event on Tuesday, a first according to TGMREIS, was organised in seven districts. The move was a collaboration with United Welfare Hyderabad, Centific, and Swinfy. Students were trained with the objective of familiarising them with emerging technologies and their real-world applications.Students presented several Al-based projects which focused on environment, education and and social issues.Minister for Minorities Welfare Mohammed Azharuddin lauded students for their efforts. He urged them to explore avenues and continue to explore, innovate and ideate so that they can contribute to society.",
      "url": "https://www.thehindu.com/news/national/telangana/tgmreis-students-showcase-ai-projects-at-literacy-event/article70780699.ece",
      "image": "https://www.thehindu.com/theme/images/og-image.png",
      "published_at": "2026-03-24T17:41:44.000Z",
      "source": "The Hindu Telangana",
      "category": "telangana",
      "language": "en",
      "title_te": "TGMREIS విద్యార్థులు అక్షరాస్యత కార్యక్రమంలో AI ప్రాజెక్ట్‌లను ప్రదర్శిస్తారు",
      "summary_te": "తెలంగాణ మైనారిటీస్ రెసిడెన్షియల్ ఎడ్యుకేషనల్ ఇన్‌స్టిట్యూషన్స్ సొసైటీ (TGMREIS)కి చెందిన 2,000 మందికి పైగా పాఠశాల విద్యార్థులు కృత్రిమ మేధస్సు యొక్క అక్షరాస్యతను కలిగి ఉన్నారు మరియు వారు అభివృద్ధి చేసిన అల్-ఆధారిత అప్లికేషన్‌లు మరియు డిజిటల్ ప్రాజెక్ట్‌లను ప్రదర్శించారు. TGMREIS ప్రకారం మంగళవారం అల్ లిటరసీ షోకేస్ ఈవెంట్‌ను మొదటిసారిగా ఏడు జిల్లాల్లో నిర్వహించారు. యునైటెడ్ వెల్ఫేర్ హైదరాబాద్, సెంటిఫిక్ మరియు స్విన్‌ఫై సహకారంతో ఈ చర్య జరిగింది. విద్యార్ధులకు అభివృద్ధి చెందుతున్న సాంకేతికతలు మరియు వాటి వాస్తవ-ప్రపంచ అనువర్తనాలతో పరిచయం కల్పించే లక్ష్యంతో శిక్షణ పొందారు. విద్యార్థులు పర్యావరణం, విద్య మరియు సామాజిక సమస్యలపై దృష్టి సారించే అనేక అల్-ఆధారిత ప్రాజెక్ట్‌లను ప్రదర్శించారు. మైనారిటీల సంక్షేమ శాఖ మంత్రి మహ్మద్ అజారుద్దీన్ విద్యార్థుల కృషిని అభినందించారు. వారు సమాజానికి దోహదపడే మార్గాలను అన్వేషించాలని మరియు అన్వేషించడం, ఆవిష్కరణలు మరియు ఆలోచనలను కొనసాగించాలని ఆయన వారిని కోరారు.",
      "translated": true
    },
    {
      "id": "82fb003e4b01027458a3b4fd2f638738",
      "title": "Sports build character, career paths, says former international badminton player",
      "summary": "Former international badminton player P. Manoj Kumar emphasised the transformative power of sports in shaping personality and strengthening life skills, while addressing students at the 37th annual sports day celebrations of Kakatiya Institute of Technology & Science, Warangal (KITSW) on Tuesday.KITSW principal Prof. K. Ashoka Reddy highlighted the institution’s continued emphasis on holistic student development.Former MLA and KITSW additional secretary Vodithala Satish Kumar encouraged students to uphold emotional balance, spiritual values, discipline, and good conduct.During the 2025-2026 academic year, more than 40 sports and games were conducted. A total of 12 trophies and over 500 medals were awarded to the winners across various categories, along with an additional 50 medals for special sports events.",
      "url": "https://www.thehindu.com/news/national/telangana/sports-build-character-career-paths-says-former-international-badminton-player/article70780814.ece",
      "image": "https://www.thehindu.com/theme/images/og-image.png",
      "published_at": "2026-03-24T17:09:16.000Z",
      "source": "The Hindu Telangana",
      "category": "telangana",
      "language": "en",
      "title_te": "క్రీడలు వ్యక్తిత్వాన్ని, కెరీర్ పథాలను నిర్మిస్తాయని మాజీ అంతర్జాతీయ బ్యాడ్మింటన్ క్రీడాకారుడు చెప్పారు",
      "summary_te": "మంగళవారం వరంగల్‌లోని కాకతీయ ఇన్‌స్టిట్యూట్ ఆఫ్ టెక్నాలజీ అండ్ సైన్స్ (కిట్స్‌డబ్ల్యూ) 37వ వార్షిక క్రీడా దినోత్సవ వేడుకల్లో విద్యార్థులను ఉద్దేశించి ప్రసంగిస్తూ, వ్యక్తిత్వాన్ని, జీవన నైపుణ్యాలను బలోపేతం చేయడంలో క్రీడల పరివర్తన శక్తిని మాజీ అంతర్జాతీయ బ్యాడ్మింటన్ క్రీడాకారుడు పి.మనోజ్ కుమార్ నొక్కిచెప్పారు. వొడితల సతీష్ కుమార్ విద్యార్థులు భావోద్వేగ సమతుల్యత, ఆధ్యాత్మిక విలువలు, క్రమశిక్షణ మరియు మంచి ప్రవర్తనను కొనసాగించాలని ప్రోత్సహించారు. 2025-2026 విద్యా సంవత్సరంలో, 40 కంటే ఎక్కువ క్రీడలు మరియు ఆటలు నిర్వహించబడ్డాయి. వివిధ విభాగాల్లో విజేతలకు మొత్తం 12 ట్రోఫీలు మరియు 500 పైగా పతకాలు, ప్రత్యేక క్రీడా కార్యక్రమాల కోసం అదనంగా 50 పతకాలు అందించబడ్డాయి.",
      "translated": true
    },
    {
      "id": "aac701bf10869b159cc32811384baf31",
      "title": "Pelting hailstorm and squall of rain bring Hyderabad to a standstill",
      "summary": "Heavy rain accompanied by a hailstorm lashed several parts of Hyderabad on the evening of Tuesday (March 24) leaving many areas waterlogged and triggering severe traffic congestion across the city. Commuters spent hours travelling from their workplaces to homes. Many people took to social media showing the size of the hail caught by them.The downpour coincided with peak evening hours, when office-goers were returning home, worsening the situation on major roads. Traffic came to a near standstill at several locations, with long queues of vehicles reported across key stretches. In the IT corridor around Gachibowli, Biodiversity Junction, commuters reported that only a stream of red tail lights was visible amid the gridlock.",
      "url": "https://www.thehindu.com/news/cities/Hyderabad/hailstorm-sudden-showers-across-hyderabad-send-commuters-scurrying-on-march-24-evening/article70780093.ece",
      "image": "https://th-i.thgim.com/public/incoming/pp6v75/article70780416.ece/alternates/LANDSCAPE_1200/_DSC8902.JPG",
      "published_at": "2026-03-24T16:55:15.000Z",
      "source": "The Hindu Telangana",
      "category": "telangana",
      "language": "en",
      "title_te": "వడగళ్ల వాన, కుండపోత వర్షంతో హైదరాబాద్‌ స్తంభించింది",
      "summary_te": "మంగళవారం (మార్చి 24) సాయంత్రం హైదరాబాద్‌లోని పలు ప్రాంతాల్లో వడగళ్ల వానతో కూడిన భారీ వర్షం కురిసింది. ప్రయాణికులు తమ కార్యాలయాల నుంచి ఇళ్లకు గంటల తరబడి ప్రయాణించారు. చాలా మంది వ్యక్తులు తాము పట్టుకున్న వడగళ్ల పరిమాణాన్ని చూపుతూ సోషల్ మీడియాలోకి వచ్చారు. ఆఫీసులకు వెళ్లినవారు ఇంటికి తిరిగి వస్తున్న సమయంలో పీక్ సాయంత్రం సమయంలో కురిసిన వర్షం ప్రధాన రహదారులపై పరిస్థితిని మరింత దిగజార్చింది. కీలకమైన ప్రాంతాలలో వాహనాలు పెద్ద క్యూలో నిలవడంతో పలు ప్రాంతాల్లో ట్రాఫిక్ దాదాపుగా నిలిచిపోయింది. గచ్చిబౌలి, బయోడైవర్సిటీ జంక్షన్ చుట్టూ ఉన్న ఐటీ కారిడార్‌లో గ్రిడ్‌లాక్ మధ్య ఎర్రటి టెయిల్ లైట్ల స్ట్రీమ్ మాత్రమే కనిపిస్తుందని ప్రయాణికులు నివేదించారు.",
      "translated": true
    },
    {
      "id": "c7943d25871cfb5a48c1be96b81ab350",
      "title": "Bhadrakali temple works to be completed by year-end: Sridhar Babu",
      "summary": "Minister for IT, Industries and Legislative Affairs D. Sridhar Babu on Tuesday said that all development works at the Bhadrakali temple in Warangal would be completed by the end of the year.Responding to a question raised by MLC Pochampalli Srinivas Reddy during Question Hour in the Legislative Council, the Minister said that Minister for Endowments Konda Surekha and Minister for Revenue Ponguleti Srinivas Reddy had conducted several review meetings, visited the temple, and provided guidance to officials on the works.Mr. Sridhar Babu said the State government was committed to restoring the historic and spiritual significance of the temple. He assured that all works, including mada streets, construction of a compound wall, gardening, and creation of public amenities, would be completed without shortcomings.“We will ensure that all works are taken up on a fast track and completed as promised,” he said.The Minister also pointed out that the previous government had issued Government Orders (GOs) allocating ₹30 crore under the Bhadrakali temple master plan, but the funds were not released, leaving the plan unimplemented.“Now, we have allocated the necessary funds and are committed to the temple’s development,” he added.",
      "url": "https://www.thehindu.com/news/national/telangana/bhadrakali-temple-works-to-be-completed-by-year-end-sridhar-babu/article70781110.ece",
      "image": "https://www.thehindu.com/theme/images/og-image.png",
      "published_at": "2026-03-24T16:41:46.000Z",
      "source": "The Hindu Telangana",
      "category": "telangana",
      "language": "en",
      "title_te": "భద్రకాళి ఆలయ పనులు ఏడాది చివరి నాటికి పూర్తి: శ్రీధర్ బాబు",
      "summary_te": "వరంగల్‌లోని భద్రకాళి ఆలయంలో అభివృద్ధి పనులన్నీ ఈ ఏడాది చివరికల్లా పూర్తిచేస్తామని ఐటీ, పరిశ్రమలు, శాసనసభా వ్యవహారాల శాఖ మంత్రి డి.శ్రీధర్‌బాబు తెలిపారు.శాసన మండలిలో ప్రశ్నోత్తరాల సమయంలో ఎమ్మెల్సీ పోచంపల్లి శ్రీనివాస్‌రెడ్డి అడిగిన ప్రశ్నకు దేవాదాయ శాఖ మంత్రి కొండా సురేఖతో కలిసి మంత్రి కొండా సురేఖతో సమీక్ష జరిపారు. దేవాలయం, మరియు పనులపై అధికారులకు మార్గదర్శకత్వం అందించారు. ఆలయ చారిత్రక, ఆధ్యాత్మిక విశిష్టతను పునరుద్ధరించేందుకు రాష్ట్ర ప్రభుత్వం కట్టుబడి ఉందని శ్రీధర్‌బాబు తెలిపారు. మాడ వీధులు, కాంపౌండ్‌ వాల్‌ నిర్మాణం, గార్డెనింగ్‌, ప్రజావసరాల కల్పనతో పాటు అన్ని పనులు లోటుపాట్లు లేకుండా పూర్తి చేస్తామని హామీ ఇచ్చారు. అన్ని పనులు త్వరితగతిన చేపట్టి వాగ్దానం చేసినట్లుగా పూర్తిచేస్తాం.గత ప్రభుత్వం భద్రకాళి ఆలయ మాస్టర్‌ ప్లాన్‌ కింద రూ.30 కోట్లు కేటాయిస్తూ ఉత్తర్వులు జారీ చేసిందని మంత్రి దృష్టికి తెచ్చారు. అమలు కాలేదు. \"ఇప్పుడు, మేము అవసరమైన నిధులను కేటాయించాము మరియు ఆలయ అభివృద్ధికి కట్టుబడి ఉన్నాము,\" అన్నారాయన.",
      "translated": true
    },
    {
      "id": "f27558d1f6e68bddd3504fcb015e73e4",
      "title": "Release funds for Musi and 7,444 km sewerage network: MP in AMRUT review meeting",
      "summary": "Telangana Member of Parliament Chamala Kiran Kumar Reddy urged the Union Government to grant immediate approvals for key urban infrastructure projects in the State during a review meeting of AMRUT and AMRUT 2.0 conducted by the Parliament Standing Committee on Housing and Urban Affairs.Mr. Reddy pressed for expediting clearance for the Hyderabad Sewerage Master Plan, which proposes a 7,444-kilometre sewerage network at an estimated cost of ₹17,212 crore. He also highlighted that the Musi River Rejuvenation Project, with an estimated outlay of ₹4,000 crore, is currently pending approval from the Centre.The Hyderabad Sewerage Master Plan is aimed at strengthening the city’s underground drainage infrastructure, while the Musi River project seeks to restore and rejuvenate the river ecosystem, improve sanitation and enhance environmental sustainability.“These projects are crucial for public health, environmental protection and sustainable urban development. The Union Government should accord approvals without further delay and release the required funds at the earliest,” Mr. Reddy said.",
      "url": "https://www.thehindu.com/news/national/telangana/release-funds-for-musi-and-7444-km-sewerage-network-mp-in-amrut-review-meeting/article70780919.ece",
      "image": "https://th-i.thgim.com/public/incoming/gz4mv5/article70781027.ece/alternates/LANDSCAPE_1200/DSC4565.jpg",
      "published_at": "2026-03-24T16:11:58.000Z",
      "source": "The Hindu Telangana",
      "category": "telangana",
      "language": "en",
      "title_te": "మూసీ, 7,444 కి.మీ సీవరేజీ నెట్‌వర్క్‌కు నిధులు విడుదల: అమృత్ సమీక్ష సమావేశంలో ఎంపీ",
      "summary_te": "హౌసింగ్‌ అండ్‌ అర్బన్‌ అఫైర్స్‌పై పార్లమెంట్‌ స్టాండింగ్‌ కమిటీ నిర్వహించిన అమృత్‌, అమృత్‌ 2.0 సమీక్షా సమావేశంలో రాష్ట్రంలోని కీలకమైన అర్బన్‌ ఇన్‌ఫ్రాస్ట్రక్చర్‌ ప్రాజెక్టులకు వెంటనే అనుమతులు మంజూరు చేయాలని తెలంగాణ పార్లమెంటు సభ్యుడు చామల కిరణ్‌కుమార్‌రెడ్డి కేంద్ర ప్రభుత్వాన్ని కోరారు. ₹17,212 కోట్ల అంచనా వ్యయంతో 7,444 కిలోమీటర్ల మురుగునీటి నెట్‌వర్క్‌ను ప్రతిపాదించిన హైదరాబాద్ సీవరేజ్ మాస్టర్ ప్లాన్‌కు క్లియరెన్స్‌ను వేగవంతం చేయాలని రెడ్డి ఒత్తిడి చేశారు. మూసీ నది పునరుజ్జీవన ప్రాజెక్ట్, ₹ 4,000 కోట్ల అంచనా వ్యయంతో ప్రస్తుతం కేంద్రం నుండి అనుమతి పెండింగ్‌లో ఉందని కూడా ఆయన హైలైట్ చేశారు. హైదరాబాద్ సివరేజ్ మాస్టర్ ప్లాన్ నగరం యొక్క భూగర్భ డ్రైనేజీ మౌలిక సదుపాయాలను బలోపేతం చేయడానికి ఉద్దేశించబడింది, మూసీ నది ప్రాజెక్ట్ నది పర్యావరణ వ్యవస్థను పునరుద్ధరించడానికి మరియు పునరుజ్జీవింపజేయడానికి ప్రయత్నిస్తుంది. ప్రజారోగ్యం, పర్యావరణ పరిరక్షణ మరియు స్థిరమైన పట్టణాభివృద్ధికి కీలకమైన కేంద్రప్రభుత్వం మరింత ఆలస్యం చేయకుండా అనుమతులు ఇవ్వాలి మరియు అవసరమైన నిధులను త్వరగా విడుదల చేయాలి” అని శ్రీ రెడ్డి అన్నారు.",
      "translated": true
    },
    {
      "id": "defa51ddeae8da7f1894a1652c710262",
      "title": "Telangana govt employees to get up to 20% discount from companies on EV purchase: Transport Minister",
      "summary": "Telangana Government employees will get up to 20% discount on purchase of two- and four-wheeler electric vehicles (EVs) from some companies. Transport Minister Ponnam Prabhakar announced on Tuesday (March 24, 2026) that this was facilitated after multiple rounds of negotiations with leading EV manufacturers including Mahindra Electric, Ola Electric, Gravton Motors, and Ather Energy.Addressing media in Hyderabad, the Minister said that this is a first in India, where a State government negotiated discounts from Original Equipment Manufacturers (OEMs) for its employees to purchase EVs. The discount is secured through OEM negotiations under a bulk institutional framework and does not involve direct budgetary subsidy, as per official communication,The government already implemented an EV policy providing 100% exemption from road tax and registration fees for electric vehicles, including two-wheelers, four-wheelers, taxis, autorickshaws, goods carriers, tractors, and buses. “With the additional [up to] 20% purchase discount, on top of the existing 100% exemption from road tax and registration fees, Telangana is making EV ownership among the most affordable in the country. By empowering government employees as early adopters, we are accelerating the transition towards cleaner mobility across society,” said Mr. Prabhakar.Since implementation of the EV policy, 1,15,551 EVs were sold and the government incurred a loss of ₹925.94 crore. Yet, the government encourages EV adoption, he said.The Transport Minister said that to support the transition to EVs, charging infrastructure will be expanded across the state, including at government offices, major public parking spaces.On the occasion, he spoke about other initiatives of the government including a mandate to hire or purchase only EVs for government department within Core Urban Region (CORE), 2,800 electric buses operated as part of its public transport fleet and the initiative to retrofit nearly one-lakh auto-rickshaws - running on petrol, diesel or gas will be retrofitted - with electric kits.",
      "url": "https://www.thehindu.com/news/national/telangana/telangana-govt-employees-to-get-10-20-discount-from-companies-on-ev-purchase-transport-minister/article70779000.ece",
      "image": "https://th-i.thgim.com/public/incoming/k2nlq9/article70779443.ece/alternates/LANDSCAPE_1200/_DSC0084.JPG",
      "published_at": "2026-03-24T16:07:43.000Z",
      "source": "The Hindu Telangana",
      "category": "telangana",
      "language": "en",
      "title_te": "తెలంగాణ ప్రభుత్వ ఉద్యోగులు EV కొనుగోలుపై కంపెనీల నుండి 20% వరకు తగ్గింపు: రవాణా మంత్రి",
      "summary_te": "తెలంగాణ ప్రభుత్వ ఉద్యోగులు కొన్ని కంపెనీల నుండి ద్విచక్ర మరియు నాలుగు చక్రాల ఎలక్ట్రిక్ వాహనాల (EVలు) కొనుగోలుపై 20% వరకు తగ్గింపు పొందుతారు. మహీంద్రా ఎలక్ట్రిక్‌, ఓలా ఎలక్ట్రిక్‌, గ్రావ్‌టన్‌ మోటార్స్‌, ఏథర్‌ ఎనర్జీ వంటి ప్రముఖ EV తయారీదారులతో పలు దఫాలుగా చర్చలు జరిపిన తర్వాత ఇది సులభతరమైందని రవాణా శాఖ మంత్రి పొన్నం ప్రభాకర్‌ మంగళవారం (మార్చి 24, 2026) ప్రకటించారు. హైదరాబాద్‌లో మీడియాను ఉద్దేశించి మంత్రి అన్నారు. EVలను కొనుగోలు చేయడానికి తయారీదారులు (OEMలు) దాని ఉద్యోగుల కోసం. డిస్కౌంట్ భారీ సంస్థాగత ఫ్రేమ్‌వర్క్‌లో OEM చర్చల ద్వారా పొందబడుతుంది మరియు అధికారిక కమ్యూనికేషన్ ప్రకారం, ప్రభుత్వం ఇప్పటికే EV విధానాన్ని అమలు చేసింది, ఇది రహదారి పన్ను మరియు రిజిస్ట్రేషన్ ఫీజుల నుండి 100% మినహాయింపును అందిస్తుంది, ఇందులో ద్విచక్ర వాహనాలు, నాలుగు చక్రాల వాహనాలు, టాక్సీలు, ఆటోరిక్షాలు మరియు గూడ్స్ క్యారియర్ బస్సులు, గూడ్స్ క్యారియర్. \"అదనపు [అదనపు] 20% కొనుగోలు తగ్గింపుతో, రహదారి పన్ను మరియు రిజిస్ట్రేషన్ రుసుము నుండి ఇప్పటికే ఉన్న 100% మినహాయింపుతో, తెలంగాణ EV యాజమాన్యాన్ని దేశంలోనే అత్యంత సరసమైనదిగా చేస్తోంది. ప్రభుత్వ ఉద్యోగులను ముందస్తుగా స్వీకరించే వారిగా, మేము సమాజం అంతటా క్లీనర్ మొబిలిటీ వైపు పరివర్తనను వేగవంతం చేస్తున్నాము\" అని శ్రీ ప్రభాకర్ చెప్పారు. విక్రయించబడింది మరియు ప్రభుత్వం ₹925.94 కోట్ల నష్టాన్ని చవిచూసింది. అయినప్పటికీ, ప్రభుత్వం EVల స్వీకరణను ప్రోత్సహిస్తుందని ఆయన అన్నారు.ఈవీలకు మారడానికి మద్దతుగా, ప్రభుత్వ కార్యాలయాలు, ప్రధాన పబ్లిక్ పార్కింగ్ స్థలాలతో సహా రాష్ట్రవ్యాప్తంగా ఛార్జింగ్ మౌలిక సదుపాయాలను విస్తరింపజేస్తామని రవాణా శాఖ మంత్రి తెలిపారు. దాని ప్రజా రవాణా సముదాయంలో భాగంగా మరియు పెట్రోల్, డీజిల్ లేదా గ్యాస్‌తో నడిచే దాదాపు లక్ష ఆటో-రిక్షాలను ఎలక్ట్రిక్ కిట్‌లతో రీట్రోఫిట్ చేయడం ప్రారంభించింది.",
      "translated": true
    },
    {
      "id": "f72be0e652c8e30c151d509f4021f61d",
      "title": "Deputy CM tears into BRS ‘failures’ during its 10-year rule",
      "summary": "Bhatti Vikramarka flays the Opposition party for boycotting his reply on Budget debate, targets BJP too",
      "url": "https://www.thehindu.com/news/national/telangana/deputy-cm-tears-into-brs-failures-during-its-10-year-rule/article70780867.ece",
      "image": null,
      "published_at": "2026-03-24T16:01:51.000Z",
      "source": "The Hindu Telangana",
      "category": "telangana",
      "language": "en",
      "title_te": "డిప్యూటీ సీఎం పదేళ్ల పాలనలో బీఆర్‌ఎస్‌ వైఫల్యాలను ఎండగట్టారు",
      "summary_te": "బడ్జెట్ చర్చపై తన ప్రత్యుత్తరాన్ని బహిష్కరించినందుకు ప్రతిపక్ష పార్టీని భట్టి విక్రమార్క, బిజెపిని కూడా లక్ష్యంగా చేసుకున్నారు",
      "translated": true
    },
    {
      "id": "00ef1c570728d85b89e86e515fc31438",
      "title": "KTR defends E-car race, claims chargesheet doesn’t name anyone",
      "summary": "HyderabadBharat Rashtra Samithi (BRS) working president K.T. Rama Rao said that the Formula-E case is “completely baseless and lacks substance”, and pointed out that “even the government has admitted in its chargesheet that there was no wrong-doing”.“The ₹45 crore transferred from a bank in Telangana remains safe in the designated account. Not a single rupee has been diverted,” he said during an informal chat with reporters in the Assembly on Tuesday.KTR accused the government of exaggerating facts and misleading the public. “They are projecting ₹45 crore as ₹600-₹700 crore to create confusion. But, people of Telangana will not believe such fabricated claims,” he said, and questioned why no individual has been named as a beneficiary in the chargesheet. He suggested that the government could retrieve the funds, if required, as they remain secure in the organisation’s account.The former Minister alleged that the revival of the Formula-E case chargesheet was a deliberate attempt by the Congress government to divert public attention from the BRS demand to grant legal status to the “Six Guarantees” through a Private Member Bill.He further stated that the government was cornered after BRS exposed that the first file signed by the Chief Minister was missing.Defending the E-car race initiative, he highlighted that the Formula-E race was brought to Hyderabad to enhance the city’s global reputation and attract large-scale investments in the EV sector. “The event generated nearly ₹700 crore economic benefits within a week, as confirmed by Nielsen. It was a prestigious race that positioned Hyderabad on the global map,” he said.KTR expressed confidence that the Formula-E case would not stand in court and accused the government of targeting him with a political vendetta by harassing officials. “We have complete faith in the judiciary. Justice will prevail in the end.”",
      "url": "https://www.thehindu.com/news/national/telangana/ktr-defends-e-car-race-claims-chargesheet-doesnt-name-anyone/article70780857.ece",
      "image": "https://www.thehindu.com/theme/images/og-image.png",
      "published_at": "2026-03-24T15:51:50.000Z",
      "source": "The Hindu Telangana",
      "category": "telangana",
      "language": "en",
      "title_te": "కేటీఆర్ ఈ-కార్ రేస్‌ను సమర్థించారు, ఛార్జిషీట్‌లో ఎవరి పేరు లేదు",
      "summary_te": "హైదరాబాద్‌భారత్‌ రాష్ట్ర సమితి (బీఆర్‌ఎస్‌) వర్కింగ్‌ ప్రెసిడెంట్‌ కె.టి. ఫార్ములా-ఇ కేసు పూర్తిగా నిరాధారమైనదని, ఇందులో ఎలాంటి వాస్తవం లేదని, ఎలాంటి తప్పు జరగలేదని ప్రభుత్వం కూడా తన చార్జిషీట్‌లో అంగీకరించిందని రామారావు అన్నారు. తెలంగాణలోని బ్యాంకు నుంచి బదిలీ అయిన ₹45 కోట్లు నిర్ణీత ఖాతాలో భద్రంగా ఉన్నాయని, ఒక్క రూపాయి కూడా పక్కదారి పట్టలేదని ఆయన మంగళవారం అసెంబ్లీలో అనధికారికంగా అసెంబ్లీలో పేర్కొన్నారు. ప్రజలను తప్పుదోవ పట్టిస్తున్నారు. గందరగోళం సృష్టించేందుకు ₹ 45 కోట్లను ₹ 600- ₹ 700 కోట్లుగా అంచనా వేస్తున్నారు. కానీ, తెలంగాణ ప్రజలు ఇలాంటి కల్పిత వాదనలను నమ్మరు, మరియు చార్జిషీట్‌లో ఏ వ్యక్తిని లబ్ధిదారునిగా ఎందుకు పేర్కొనలేదని ఆయన ప్రశ్నించారు. సంస్థ ఖాతాలో భద్రంగా ఉన్నందున అవసరమైతే ప్రభుత్వం వాటిని తిరిగి పొందవచ్చని ఆయన సూచించారు. ఫార్ములా-ఇ కేసు ఛార్జిషీట్ పునరుద్ధరణ కాంగ్రెస్ ప్రభుత్వం ఉద్దేశపూర్వకంగా చేసిన ప్రయత్నం అని ఆరోపించింది. ముఖ్యమంత్రి సంతకం తప్పిపోయింది. ఈ-కార్ రేస్ చొరవను సమర్థిస్తూ, నగరం యొక్క ప్రపంచ ఖ్యాతిని పెంపొందించడానికి మరియు EV రంగంలో పెద్ద ఎత్తున పెట్టుబడులను ఆకర్షించడానికి ఫార్ములా-E రేసును హైదరాబాద్‌కు తీసుకువచ్చినట్లు ఆయన హైలైట్ చేశారు. \"నీల్సన్ ధృవీకరించినట్లుగా, ఈ ఈవెంట్ వారంలో దాదాపు ₹700 కోట్ల ఆర్థిక ప్రయోజనాలను అందించింది. ఇది ప్రతిష్టాత్మకమైన జాతిగా హైదరాబాద్‌ను ప్రపంచ పటంలో ఉంచింది,\" అని ఆయన అన్నారు. ఫార్ములా-E కేసు కోర్టులో నిలబడదని KTR విశ్వాసం వ్యక్తం చేశారు మరియు ప్రభుత్వం రాజకీయ ప్రతీకారంతో అధికారులను వేధింపులకు గురిచేస్తోందని ఆరోపించారు. \"మాకు న్యాయవ్యవస్థపై పూర్తి విశ్వాసం ఉంది. చివరికి న్యాయమే గెలుస్తుంది.\"",
      "translated": true
    }
  ]
}